mauve/__init__.py
mauve/bst.py
mauve/decorators.py
mauve/settings.py
mauve/utils.py
mauve/bin/__init__.py
mauve/bin/compress_files.py
mauve/bin/convert_filenames.py
mauve/bin/epub_slimmer.py
mauve/bin/generate_rag.py
mauve/bin/mobi_to_epub.py
mauve/bin/scrape_author_nationality.py
mauve/bin/scrape_awards.py
mauve/bin/scrape_calibre.py
mauve/bin/scrape_eye.py
mauve/bin/scrape_goodreads.py
mauve/bin/to_text.py
mauve/constants/__init__.py
mauve/constants/cliches.py
mauve/constants/names.py
mauve/constants/profanity.py
mauve/constants/synonym.py
mauve/constants/tokens.py
mauve/constants/vader.py
mauve/learn/__init__.py
mauve/learn/generate.py
mauve/learn/tagged_docs.py
mauve/learn/utils.py
mauve/models/__init__.py
mauve/models/comparitor.py
mauve/models/deptree.py
mauve/models/entity.py
mauve/models/generic.py
mauve/models/line.py
mauve/models/person.py
mauve/models/segment.py
mauve/models/sentence.py
mauve/models/speech.py
mauve/models/synonym.py
mauve/models/text.py
mauve/models/books/__init__.py
mauve/models/books/book.py
mauve/models/books/review.py
mauve/models/books/tag.py
mauve/preprocess/__init__.py
mauve/preprocess/contractions.py
mauve/preprocess/idioms.py
mauve/preprocess/number_convert.py
mauve/preprocess/phrases.py
mauve/preprocess/spelling.py
mauve/preprocess/utils.py
mauve/preprocess/w2n.py
mauve/preprocess/constants/__init__.py
mauve/preprocess/constants/contractions.py
mauve/preprocess/constants/idioms.py
mauve/preprocess/constants/phrases.py
mauve/preprocess/constants/replacements.py
mauve/preprocess/constants/spelling.py
mauve/rag/__init__.py
mauve/rag/model.py
mauve/structure/__init__.py
mauve/structure/assignment.py
mauve/structure/conditional.py
noba_mauve-0.0.7.dist-info/METADATA
noba_mauve-0.0.7.dist-info/WHEEL
noba_mauve-0.0.7.dist-info/entry_points.txt
noba_mauve-0.0.7.dist-info/top_level.txt
noba_mauve-0.0.7.dist-info/RECORD
